frxx_view/__init__.py
frxx_view/main.py
frxx_view-0.0.1.dist-info/licenses/LICENSE
frxx_view-0.0.1.dist-info/METADATA
frxx_view-0.0.1.dist-info/WHEEL
frxx_view-0.0.1.dist-info/top_level.txt
frxx_view-0.0.1.dist-info/RECORD
